{"name": "pandas-on-spark", "category": "data-science", "title": "Pandas API with spark backend (Koalas)", "description": "Let you Data Science team scale to TB of data while working with Pandas API, without having to learn & move to another framework.", "fullDescription": "Despite being one of the most popular framework for data analysis, Pandas isn't distributed and can't process TB of data. Databricks solves this issues by allowing users to leverage pandas API while processing the data with spark distributed engine. This demo show you how to process big data using Pandas API (previously known as Koalas).", "bundle": true, "tags": [{"ds": "Data Science"}], "notebooks": [{"path": "_resources/00-setup", "pre_run": false, "publish_on_website": false, "add_cluster_setup_cell": false, "title": "Setup", "description": "Init data for demo."}, {"path": "_resources/01-load-data", "pre_run": false, "publish_on_website": false, "add_cluster_setup_cell": false, "title": "Setup", "description": "Init data for demo."}, {"path": "01-pyspark-pandas-api-koalas", "pre_run": true, "publish_on_website": true, "add_cluster_setup_cell": true, "title": "Pandas on Spark (Koalas)", "description": "Scale & accelerate your Pandas transformations"}, {"path": "_resources/00-global-setup", "title": "Global init", "description": "Global init", "pre_run": false, "publish_on_website": false, "add_cluster_setup_cell": false, "parameters": {}, "depends_on_previous": true, "libraries": []}]}